database_factory/__init__.py
database_factory/engine_factory.py
database_factory_snehal-0.1.0.dist-info/licenses/LICENSE
database_factory_snehal-0.1.0.dist-info/METADATA
database_factory_snehal-0.1.0.dist-info/WHEEL
database_factory_snehal-0.1.0.dist-info/top_level.txt
database_factory_snehal-0.1.0.dist-info/RECORD
