Metadata-Version: 2.4
Name: database-factory-snehal
Version: 0.1.0
Summary: A robust factory for creating self-destructing temporary SQLite databases for testing.
Author-email: SnehalPradhan <snehalpradhan23@gmail.com>
Project-URL: Homepage, https://github.com/yourusername/database-factory
Project-URL: Bug Tracker, https://github.com/yourusername/database-factory/issues
Classifier: License :: OSI Approved :: MIT License
Classifier: Programming Language :: Python :: 3
Classifier: Operating System :: OS Independent
Classifier: Intended Audience :: Developers
Classifier: Topic :: Software Development :: Testing
Classifier: Topic :: Database
Requires-Python: >=3.7
License-File: LICENSE
Requires-Dist: sqlalchemy>=1.4.0
Dynamic: license-file
